pydot_flow/__about__.py
pydot_flow/__init__.py
pydot_flow/chart.py
pydot_flow/node.py
pydot_flow-0.6.1.dist-info/METADATA
pydot_flow-0.6.1.dist-info/WHEEL
pydot_flow-0.6.1.dist-info/licenses/LICENSE
pydot_flow-0.6.1.dist-info/RECORD
