Metadata-Version: 2.4
Name: pydot_flow
Version: 0.6.1
Summary: Pydot _flow_ makes it a little easier to assemble simple flowing graphs using Pydot.
Project-URL: Homepage, https://github.com/far-analytics/pydot-flow
Project-URL: Bug Tracker, https://github.com/far-analytics/pydot-flow/issues
Author-email: Adam Patterson <adpatter2000@gmail.com>
License-File: LICENSE
Classifier: License :: OSI Approved :: MIT License
Classifier: Operating System :: OS Independent
Classifier: Programming Language :: Python :: 3
Requires-Python: >=3.9
Requires-Dist: pydot==2.*
